<level>
  <type>section</type>
  <num>16-3120</num>
  <heading>TRANSCRIPTS OF HEARINGS (ยง 16-3120)</heading>
  <level>
    <num>3120.1.</num>
    <text>Transcripts of hearings may be ordered from the Director on a form prescribed by the Director.</text>
  </level>
  <level>
    <num>3120.2.</num>
    <text>The fee for transcripts shall be three dollars and fifty cents ($3.50) per page.</text>
  </level>
  <level>
    <num>3120.3.</num>
    <text>A person ordering a transcript shall submit a deposit of fifty dollars ($50) with the order.</text>
  </level>
  <level>
    <num>3120.4.</num>
    <text>When the cost of a transcript has been determined to be less than the amount of the transcript deposit, the Director shall refund the amount by which the deposit exceeds the cost of the transcript.</text>
  </level>
  <level>
    <num>3120.5.</num>
    <text>When the cost of a transcript is determined to exceed the amount of the transcript deposit, the person ordering the transcript shall pay the balance prior to the issuance of the transcript.</text>
  </level>
  <level>
    <num>3120.6.</num>
    <text>The Director may waive all or part of the cost of a transcript in cases of financial hardship or other appropriate circumstances, as determined by the Director.</text>
  </level>
  <level>
    <type>annotations</type>
    <level>
      <heading>SOURCE</heading>
      <text>Final Rulemaking published at 34 DCR 5718, 5733 (September 4, 1987).</text>
    </level>
  </level>
</level>