<level>
  <type>section</type>
  <num>17-8100</num>
  <heading>GENERAL PROVISIONS (ยง 17-8100)</heading>
  <level>
    <num>8100.1.</num>
    <text>This chapter shall apply to applicants for and holders of a license to practice as a polysomnographic technologist and application for and holders of a registration to practice as a polysomnographic technician or polysomnographic trainee.</text>
  </level>
  <level>
    <num>8100.2.</num>
    <text>Effective immediately, no person shall practice polysomnography in the District of Columbia unless he or she is licensed or registered under this chapter.</text>
  </level>
  <level>
    <num>8100.3.</num>
    <text>An applicant to practice as a polysomnographic technologist shall be licensed in accordance with ยง 8102.</text>
  </level>
  <level>
    <num>8100.4.</num>
    <text>An applicant to practice as a polysomnographic technician shall be registered in accordance with ยง 8103.</text>
  </level>
  <level>
    <num>8100.5.</num>
    <text>An applicant to practice as a polysomnographic trainee shall be registered in accordance with ยง 8104.</text>
  </level>
  <level>
    <num>8100.6.</num>
    <text>Chapters 40 (Health Occupations: General Rules), 41 (Health</text>
    <text>Occupations: Administrative Procedures), and 46 (Medicine) of this title shall supplement this chapter.</text>
    <text>Source: Notice of Final Rulemaking published at 58 DCR 3758 (April 29, 2011).</text>
  </level>
  <level>
    <type>annotations</type>
  </level>
</level>