<level>
  <type>section</type>
  <num>29-517</num>
  <heading>EMS PROVIDERS &amp;#8211; EMERGENCY MEDICAL TECHNICIAN (§ 29-517)</heading>
  <level>
    <num>517.1</num>
    <text>517.1 Each applicant for certification as an Emergency Medical Technician (EMT)hall submit an application to the Director. The application shall include:</text>
    <text>A copy of a valid NREMT-EMT (or greater) certification card;</text>
    <level>
      <num>(b)</num>
      <text>A copy of a valid AHA Health Care Provider (or equivalent) CPR card;</text>
    </level>
    <level>
      <num>(c)</num>
      <text>A completed application signed by the sponsoring EMS agency’s medicalirector; and</text>
    </level>
    <level>
      <num>(d)</num>
      <text>A check or money order made out in the appropriate fee made payable to the.C. Treasurer (if applicable).</text>
    </level>
  </level>
  <level>
    <num>517.2</num>
    <text>517.2 Upon receipt of a complete application, the Director shall review thepplication and, if approved, shall issue a D.C. EMT certification card.</text>
  </level>
  <level>
    <type>annotations</type>
    <level>
      <heading>SOURCE</heading>
      <text>Final Rulemaking published at 60 DCR 16569 (December 6, 2013).</text>
    </level>
  </level>
</level>