<level>
  <type>section</type>
  <num>31-306</num>
  <heading>VOTES (ยง 31-306)</heading>
  <level>
    <num>306.1.</num>
    <text>Action shall be taken by majority vote of the members of the Panel present and voting unless provided to the contrary in these rules or in other District of Columbia laws or regulations.</text>
  </level>
  <level>
    <num>306.2.</num>
    <text>No person may vote on Panel matters unless that person is a current member of the Panel.</text>
  </level>
  <level>
    <num>306.3.</num>
    <text>A motion to reconsider a vote may be made at the same meeting at which the vote was taken or, if otherwise in order, at the next meeting, by any member of the Panel who voted with the prevailing side on a matter.</text>
  </level>
  <level>
    <num>306.4.</num>
    <text>No proxy votes are permitted.</text>
  </level>
  <level>
    <type>annotations</type>
    <level>
      <heading>SOURCE</heading>
      <text>Final Rulemaking published at 34 DCR 6751, 6755 (October 23, 1987).</text>
    </level>
  </level>
</level>