<level>
  <type>section</type>
  <num>17-2002</num>
  <heading>PHOTOGRAPHS AND FINGERPRINTS (§ 17-2002)</heading>
  <level>
    <num>2002.1.</num>
    <text>Each individual applicant for a license as a private detective shall submit four (4) identical, full-faced photographs of himself or herself, one inch by one and one-half inches in size (1&amp;#8243; x 1 1/2&amp;#8243;), which were taken not more
      than three (3) months prior to date of application.</text>
  </level>
  <level>
    <num>2002.2.</num>
    <text>Each corporate applicant for license as a private detective shall submit the required photographs of its president and vice-president.</text>
  </level>
  <level>
    <num>2002.3.</num>
    <text>Each individual applicant for a license as a private detective shall have three (3) sets of his or her fingerprints taken by the Chief of Police.</text>
  </level>
  <level>
    <num>2002.4.</num>
    <text>Fingerprints taken under §2002.3 shall become part of the application for the license.</text>
  </level>
  <level>
    <num>2002.5.</num>
    <text>Fingerprints shall be submitted for comparison and record to the Federal Bureau of Investigation and to other authorities that the Chief of Police may deem advisable.</text>
  </level>
  <level>
    <num>2002.6.</num>
    <text>Each corporate applicant for a license as a private detective shall make its president and vice-president available to the Chief of Police for fingerprinting.</text>
  </level>
  <level>
    <type>annotations</type>
    <level>
      <heading>SOURCE</heading>
      <text>Sections 2 and 3 of Regulation 70-30, approved July 9, 1970 (17 DCR 40), 5EE DCRR, §§ 2.1 and 2.2.</text>
    </level>
  </level>
</level>