<level>
  <type>section</type>
  <num>29-916</num>
  <heading>WHO MAY PROVIDE CARE (ยง 29-916)</heading>
  <level>
    <num>916.1.</num>
    <text>The nurse-midwifery services shall meet the following requirements:</text>
    <level>
      <num>(a)</num>
      <text>Be provided by a person who is licensed as a registered nurse in the District of Columbia;</text>
    </level>
    <level>
      <num>(b)</num>
      <text>Meet the requirements of D.C. Law 6-99; and</text>
    </level>
    <level>
      <num>(c)</num>
      <text>Execute a provider agreement with the D.C. Medicaid Program.</text>
    </level>
  </level>
  <level>
    <type>annotations</type>
    <level>
      <heading>SOURCE</heading>
      <text>Final Rulemaking published at 33 DCR 5657 (September 12, 1986).</text>
    </level>
  </level>
</level>