<level>
  <type>section</type>
  <num>21-5350</num>
  <heading>PROTESTS (§ 21-5350)</heading>
  <level>
    <num>5350.1.</num>
    <text>The procedures in §§ 5351 through 5353 shall govern protests.</text>
  </level>
  <level>
    <type>annotations</type>
    <level>
      <heading>SOURCE</heading>
      <text>Emergency Rulemaking published at 46 DCR 613 (January 22, 1999) [EXPIRED]; as Final Rulemaking published at 46 DCR 7349 (September 17, 1999); as amended by Final Rulemaking published at 56 DCR 4484 (June 12, 2009).</text>
    </level>
  </level>
</level>