<level>
  <type>section</type>
  <num>28-524</num>
  <heading>PRE-HEARING RIGHTS OF RESIDENTS (ยง 28-524)</heading>
  <level>
    <num>524.1.</num>
    <text>A resident may request one (1) or more continuances of the Housing Board hearing. Each continuance shall be for three (3) work days.</text>
  </level>
  <level>
    <num>524.2.</num>
    <text>The Board administrators shall grant a request for a continuance if the resident establishes one (1) of the following:</text>
    <level>
      <num>(a)</num>
      <text>That the resident&amp;#8217;s attorney, substitute counsel, or any witness would not be available on the day of the hearing; or</text>
    </level>
    <level>
      <num>(b)</num>
      <text>That the resident could not properly prepare for the hearing in the time allotted.</text>
    </level>
  </level>
  <level>
    <num>524.3.</num>
    <text>A resident shall be entitled to be represented by counsel or substitute counsel at the Housing Hearing.</text>
  </level>
  <level>
    <num>524.4.</num>
    <text>If the resident chooses to be represented, the resident shall be given reasonable opportunity to obtain a lawyer or a law student to represent the resident at the Housing Hearing.</text>
  </level>
  <level>
    <num>524.5.</num>
    <text>Counsel shall not be provided at the expense of the Department of Corrections.</text>
  </level>
  <level>
    <type>annotations</type>
    <level>
      <heading>SOURCE</heading>
      <text>Final Rulemaking published at 28 DCR 865, 895 (February 27, 1981).</text>
    </level>
  </level>
</level>