<level>
  <type>section</type>
  <num>29-404</num>
  <heading>REVIEW OF NONCOMPETING CONTINUATION APPLICATIONS (ยง 29-404)</heading>
  <level>
    <num>404.1.</num>
    <text>Each applicant shall provide SHPDA with a copy of each application for a noncompeting continuation grant at the time the application is submitted to the federal funding agency or the Regional A-95 Clearinghouse, whichever is the earliest submission
      date.</text>
  </level>
  <level>
    <num>404.2.</num>
    <text>The SHPDA shall review and approve or disapprove an application for a noncompeting continuation grant in the following circumstances:</text>
    <level>
      <num>(a)</num>
      <text>Upon its own initiative, if the SHPDA has notified the federal funding agency of its intent to conduct the review at least nine (9) months prior to the date of a continuation grant award;</text>
    </level>
    <level>
      <num>(b)</num>
      <text>When the applicant proposes a change in the funding level of twenty percent (20%) or more from that previously approved by the federal funding agency;</text>
    </level>
    <level>
      <num>(c)</num>
      <text>When the applicant or the federal funding agency determines that there has been a substantial change in the proposed or actual use of funds; or</text>
    </level>
    <level>
      <num>(d)</num>
      <text>If no other review is made under this subsection, every five (5) years, beginning November 8, 1979.</text>
    </level>
  </level>
  <level>
    <type>annotations</type>
    <level>
      <heading>SOURCE</heading>
      <text>Final Rulemaking published at 28 DCR 1086 (March 13, 1981).</text>
    </level>
  </level>
</level>